<?xml version="1.0" encoding="UTF-8"?>
<update>
	<information>
		<versionCode>1</versionCode>
		<versionName>1.0</versionName>
		<versionTime>2015-02</versionTime>
		<apkUrl></apkUrl>
		<description>新增查课表、查阳光教育服务中心信息</description>
	</information>
	<information>
		<versionCode>2</versionCode>
		<versionName>1.0.1</versionName>
		<versionTime>2015-04</versionTime>
		<apkUrl></apkUrl>
		<description>新增查数字图书馆书籍信息</description>
	</information>
	<information>
		<versionCode>3</versionCode>
		<versionName>1.0.2</versionName>
		<versionTime>2015-08</versionTime>
		<apkUrl></apkUrl>
		<description>新增教务系统登录手机抢课等其他功能</description>
	</information>
	<information>
		<versionCode>4</versionCode>
		<versionName>1.1</versionName>
		<versionTime>2015-09-01</versionTime>
		<apkUrl>https://coding.net/u/xbdcc/p/xiaobudian/git/raw/master/HuasTools/apk/HuasTools1.1.apk</apkUrl>
		<description>新增检测更新功能</description>
	</information>
	<information>
		<versionCode>5</versionCode>
		<versionName>1.1.1</versionName>
		<versionTime>2015-09-01</versionTime>
		<apkUrl>https://coding.net/u/xbdcc/p/xiaobudian/git/raw/master/HuasTools/apk/HuasTools1.1.1.apk</apkUrl>
		<description>测试检测更新功能</description>
	</information>
	<information>
		<versionCode>6</versionCode>
		<versionName>1.1.2</versionName>
		<versionTime>2015-09-02</versionTime>
		<apkUrl>https://coding.net/u/xbdcc/p/xiaobudian/git/raw/master/HuasTools/apk/HuasTools1.1.2.apk</apkUrl>
		<description>添加百度云推送功能</description>
	</information>
	<information>
		<versionCode>7</versionCode>
		<versionName>1.1.3</versionName>
		<versionTime>2015-09-03</versionTime>
		<apkUrl>https://gitcafe.com/xbdcc/xiaobudian/raw/master/apk/HuasTools/HuasTools1.1.3.apk</apkUrl>
		<description>添加推送更新版本信息，优化一些bug</description>
	</information>
		<information>
		<versionCode>8</versionCode>
		<versionName>1.1.7</versionName>
		<versionTime>2015-09-05</versionTime>
		<apkUrl>http://xbdcc.github.io/xiaobudian/HuasTools/apk/HuasTools1.1.4.apk</apkUrl>
		<description>添加推送更新版本信息，优化一些bug</description>
	</information>
</update>
